odoo8_addon_hr_timesheet_sheet_change_period-8.0.1.0.0-py2.7-nspkg.pth
odoo8_addon_hr_timesheet_sheet_change_period-8.0.1.0.0.dist-info/top_level.txt
odoo8_addon_hr_timesheet_sheet_change_period-8.0.1.0.0.dist-info/WHEEL
odoo8_addon_hr_timesheet_sheet_change_period-8.0.1.0.0.dist-info/RECORD
odoo8_addon_hr_timesheet_sheet_change_period-8.0.1.0.0.dist-info/metadata.json
odoo8_addon_hr_timesheet_sheet_change_period-8.0.1.0.0.dist-info/DESCRIPTION.rst
odoo8_addon_hr_timesheet_sheet_change_period-8.0.1.0.0.dist-info/METADATA
odoo8_addon_hr_timesheet_sheet_change_period-8.0.1.0.0.dist-info/namespace_packages.txt
odoo_addons/hr_timesheet_sheet_change_period/README.md
odoo_addons/hr_timesheet_sheet_change_period/__openerp__.py
odoo_addons/hr_timesheet_sheet_change_period/__init__.py
odoo_addons/hr_timesheet_sheet_change_period/hr_timesheet_sheet_change_period_demo.xml
odoo_addons/hr_timesheet_sheet_change_period/i18n/hr_timesheet_sheet_change_period.pot
odoo_addons/hr_timesheet_sheet_change_period/i18n/fr.po
odoo_addons/hr_timesheet_sheet_change_period/wizard/__init__.py
odoo_addons/hr_timesheet_sheet_change_period/wizard/hr_timesheet_sheet_change_period.xml
odoo_addons/hr_timesheet_sheet_change_period/wizard/hr_timesheet_sheet_change_period.py
odoo_addons/hr_timesheet_sheet_change_period/views/hr_timesheet_sheet_view.xml
odoo_addons/hr_timesheet_sheet_change_period/tests/test_change_period.py
odoo_addons/hr_timesheet_sheet_change_period/tests/__init__.py
odoo_addons/hr_timesheet_sheet_change_period/static/description/icon.png
